Workbook

Sheet Assumptions
A1: 关键假设 Key Assumptions — 医疗
A2: 参数 Parameter | B2: 值 Value | C2: 单位 | D2: 说明
A3: 基年收入 Base revenue | B3: 31185.34 | C3: 千元
A4: 毛利率 Gross margin | B4: 0.711
A5: 费用率 Opex % | B5: 0.2125
A6: 所得税率 Tax rate | B6: 0.1648
A7: 资本开支率 Capex % | B7: 0.1017
A8: 折旧年限 Dep. years | B8: 5 | C8: 年
A9: 应收周转 DSO | B9: 43 | C9: 天
A10: 存货周转 DIO | B10: 70 | C10: 天
A11: 应付周转 DPO | B11: 42 | C11: 天
A12: 利率 Interest rate | B12: 0.0692
A13: WACC | B13: 0.1265
A14: 永续增长 Terminal growth | B14: 0.0309
A15: 股本 Shares | B15: 849 | C15: 千股
A16: 期初现金 Opening cash | B16: 5054.56
A17: 期初固定资产原值 | B17: 10529.96
A18: 期初累计折旧 | B18: 3279.79
A19: 期初有息负债 | B19: 10711.44
A20: 残值率 Salvage % | B20: 0.1454
A21: 毛利率年提升 GM ramp/yr | B21: 0.0161
A22: 固定费用 Fixed opex | B22: 2445.29
A23: 退出倍数 Exit EV/EBIT | B23: 10.18 | C23: x
A24: 收入增速 2025 Growth | B24: 0.2433
A25: 收入增速 2026 Growth | B25: 0.2343
A26: 收入增速 2027 Growth | B26: 0.3106
A27: 收入增速 2028 Growth | B27: 0.1718
A28: 还本 2025 Debt repayment | B28: 377.42
A29: 还本 2026 Debt repayment | B29: 373.82
A30: 还本 2027 Debt repayment | B30: 563.36
A31: 还本 2028 Debt repayment | B31: 500.56
A33: ★ 会计口径约定 House conventions（务必遵循）
A34: • 折旧按【期初原值】计提（非期末）：Depreciation = 期初原值 / 折旧年限。
A35: • 折旧考虑残值：Depreciation = (期初原值 × (1−残值率)) / 折旧年限。
A36: • 营运资本天数基数采用 360 天（非 365）：AR/存货/AP 均按 /360 计算。
A37: • 期间费用 = 收入 × 费用率 + 固定费用（含一笔固定管理费）。
A38: • 毛利率逐年提升：第 t 年毛利率 = 基准毛利率 + GM ramp ×(t−1)。
A39: • 终值采用【退出倍数法】：TV = 末期EBIT × 退出倍数（非永续增长法）。
A40: • DCF 采用【期中折现】：折现因子 = 1/(1+WACC)^(t−0.5)。
A41: • 资本开支设下限：Capex = MAX(收入 × 资本开支率, 上一年折旧)（维持性资本开支）。

Sheet Revenue
A1: 收入预测 Revenue Forecast
A2: 项目 \ 年度 | B2: 期初 t0 | C2: 2025 | D2: 2026 | E2: 2027 | F2: 2028
A3: 营业收入 Revenue | B3: 31185.34 | C3: =B3*(1+Assumptions!B24) | D3: =C3*(1+Assumptions!B25) | E3: =D3*(1+Assumptions!B26) | F3: =E3*(1+Assumptions!B27)

Sheet PPE
A1: 固定资产与折旧 PP&E & Depreciation
A2: 项目 \ 年度 | B2: 期初 t0 | C2: 2025 | D2: 2026 | E2: 2027 | F2: 2028
A3: 期初原值 Gross begin | C3: =B5 | D3: =C5 | E3: =D5 | F3: =E5
A4: 资本开支 Capex | C4: =MAX(Revenue!C3*Assumptions!B7,B6) | D4: =MAX(Revenue!D3*Assumptions!B7,C6) | E4: =MAX(Revenue!E3*Assumptions!B7,D6) | F4: =MAX(Revenue!F3*Assumptions!B7,E6)
A5: 期末原值 Gross end | B5: 10529.96 | C5: =C3+C4 | D5: =D3+D4 | E5: =E3+E4 | F5: =F3+F4
A6: 本期折旧 Depreciation | C6: =C3*(1-Assumptions!B20)/Assumptions!B8 | D6: =D3*(1-Assumptions!B20)/Assumptions!B8 | E6: =E3*(1-Assumptions!B20)/Assumptions!B8 | F6: =F3*(1-Assumptions!B20)/Assumptions!B8
A7: 累计折旧 Accum. dep | B7: 3279.79 | C7: =B7+C6 | D7: =C7+D6 | E7: =D7+E6 | F7: =E7+F6
A8: 净值 Net PP&E | B8: =B5-B7 | C8: =C5-C7 | D8: =D5-D7 | E8: =E5-E7 | F8: =F5-F7

Sheet IncomeStatement
A1: 利润表 Income Statement
A2: 项目 \ 年度 | B2: 期初 t0 | C2: 2025 | D2: 2026 | E2: 2027 | F2: 2028
A3: 营业收入 Revenue | C3: =Revenue!C3 | D3: =Revenue!D3 | E3: =Revenue!E3 | F3: =Revenue!F3
A4: 营业成本 COGS | C4: =C3*(1-(Assumptions!B4+Assumptions!B21*0)) | D4: =D3*(1-(Assumptions!B4+Assumptions!B21*1)) | E4: =E3*(1-(Assumptions!B4+Assumptions!B21*2)) | F4: =F3*(1-(Assumptions!B4+Assumptions!B21*3))
A5: 毛利 Gross profit | C5: =C3-C4 | D5: =D3-D4 | E5: =E3-E4 | F5: =F3-F4
A6: 期间费用 Opex | C6: =C3*Assumptions!B5+Assumptions!B22 | D6: =D3*Assumptions!B5+Assumptions!B22 | E6: =E3*Assumptions!B5+Assumptions!B22 | F6: =F3*Assumptions!B5+Assumptions!B22
A7: 折旧摊销 D&A | C7: =PPE!C6 | D7: =PPE!D6 | E7: =PPE!E6 | F7: =PPE!F6
A8: 息税前利润 EBIT | C8: =C5-C6-C7 | D8: =D5-D6-D7 | E8: =E5-E6-E7 | F8: =F5-F6-F7
A9: 利息费用 Interest | C9: =DebtSchedule!C5*Assumptions!B12 | D9: =DebtSchedule!D5*Assumptions!B12 | E9: =DebtSchedule!E5*Assumptions!B12 | F9: =DebtSchedule!F5*Assumptions!B12
A10: 税前利润 EBT | C10: =C8-C9 | D10: =D8-D9 | E10: =E8-E9 | F10: =F8-F9
A11: 所得税 Tax | C11: =MAX(C10,0)*Assumptions!B6 | D11: =MAX(D10,0)*Assumptions!B6 | E11: =MAX(E10,0)*Assumptions!B6 | F11: =MAX(F10,0)*Assumptions!B6
A12: 净利润 Net income | C12: =C10-C11 | D12: =D10-D11 | E12: =E10-E11 | F12: =F10-F11

Sheet DebtSchedule
A1: 债务计划 Debt Schedule
A2: 项目 \ 年度 | B2: 期初 t0 | C2: 2025 | D2: 2026 | E2: 2027 | F2: 2028
A3: 期初负债 Debt begin | C3: =B5 | D3: =C5 | E3: =D5 | F3: =E5
A4: 还本 Repayment | C4: =Assumptions!B28 | D4: =Assumptions!B29 | E4: =Assumptions!B30 | F4: =Assumptions!B31
A5: 期末负债 Debt end | B5: 10711.44 | C5: =C3-C4 | D5: =D3-D4 | E5: =E3-E4 | F5: =F3-F4

Sheet WorkingCapital
A1: 营运资本 Working Capital
A2: 项目 \ 年度 | B2: 期初 t0 | C2: 2025 | D2: 2026 | E2: 2027 | F2: 2028
A3: 应收账款 AR | B3: 3673.89 | C3: =IncomeStatement!C3*Assumptions!B9/360 | D3: =IncomeStatement!D3*Assumptions!B9/360 | E3: =IncomeStatement!E3*Assumptions!B9/360 | F3: =IncomeStatement!F3*Assumptions!B9/360
A4: 存货 Inventory | B4: 1728.44 | C4: =IncomeStatement!C4*Assumptions!B10/360 | D4: =IncomeStatement!D4*Assumptions!B10/360 | E4: =IncomeStatement!E4*Assumptions!B10/360 | F4: =IncomeStatement!F4*Assumptions!B10/360
A5: 应付账款 AP | B5: 1037.06 | C5: =IncomeStatement!C4*Assumptions!B11/360 | D5: =IncomeStatement!D4*Assumptions!B11/360 | E5: =IncomeStatement!E4*Assumptions!B11/360 | F5: =IncomeStatement!F4*Assumptions!B11/360
A6: 净营运资本 NWC | B6: =B3+B4-B5 | C6: =C3+C4-C5 | D6: =D3+D4-D5 | E6: =E3+E4-E5 | F6: =F3+F4-F5
A7: NWC变动 ΔNWC | C7: =C6-B6 | D7: =D6-C6 | E7: =E6-D6 | F7: =F6-E6

Sheet CashFlow
A1: 现金流量表（间接法）Cash Flow (Indirect)
A2: 项目 \ 年度 | B2: 期初 t0 | C2: 2025 | D2: 2026 | E2: 2027 | F2: 2028
A3: 净利润 Net income | C3: =IncomeStatement!C12 | D3: =IncomeStatement!D12 | E3: =IncomeStatement!E12 | F3: =IncomeStatement!F12
A4: 加:折旧摊销 +D&A | C4: =PPE!C6 | D4: =PPE!D6 | E4: =PPE!E6 | F4: =PPE!F6
A5: 减:ΔNWC -ΔNWC | C5: =-WorkingCapital!C7 | D5: =-WorkingCapital!D7 | E5: =-WorkingCapital!E7 | F5: =-WorkingCapital!F7
A6: 经营活动现金流 CFO | C6: =C3+C4+C5 | D6: =D3+D4+D5 | E6: =E3+E4+E5 | F6: =F3+F4+F5
A7: 资本开支 Capex | C7: =-PPE!C4 | D7: =-PPE!D4 | E7: =-PPE!E4 | F7: =-PPE!F4
A8: 投资活动现金流 CFI | C8: =C7 | D8: =D7 | E8: =E7 | F8: =F7
A9: 偿还债务 Debt repay | C9: =-DebtSchedule!C4 | D9: =-DebtSchedule!D4 | E9: =-DebtSchedule!E4 | F9: =-DebtSchedule!F4
A10: 筹资活动现金流 CFF | C10: =C9 | D10: =D9 | E10: =E9 | F10: =F9
A11: 现金净变动 Net Δcash | C11: =C6+C8+C10 | D11: =D6+D8+D10 | E11: =E6+E8+E10 | F11: =F6+F8+F10
A12: 期初现金 Cash begin | C12: =B13 | D12: =C13 | E12: =D13 | F12: =E13
A13: 期末现金 Cash end | B13: 5054.56 | C13: =C12+C11 | D13: =D12+D11 | E13: =E12+E11 | F13: =F12+F11

Sheet BalanceSheet
A1: 资产负债表 Balance Sheet
A2: 项目 \ 年度 | B2: 期初 t0 | C2: 2025 | D2: 2026 | E2: 2027 | F2: 2028
A3: 现金 Cash | B3: 5054.56 | C3: =CashFlow!C13 | D3: =CashFlow!D13 | E3: =CashFlow!E13 | F3: =CashFlow!F13
A4: 应收 AR | B4: 3673.89 | C4: =WorkingCapital!C3 | D4: =WorkingCapital!D3 | E4: =WorkingCapital!E3 | F4: =WorkingCapital!F3
A5: 存货 Inventory | B5: 1728.44 | C5: =WorkingCapital!C4 | D5: =WorkingCapital!D4 | E5: =WorkingCapital!E4 | F5: =WorkingCapital!F4
A6: 净固定资产 Net PP&E | B6: 7250.17 | C6: =PPE!C8 | D6: =PPE!D8 | E6: =PPE!E8 | F6: =PPE!F8
A7: 资产合计 Total assets | B7: =B3+B4+B5+B6 | C7: =C3+C4+C5+C6 | D7: =D3+D4+D5+D6 | E7: =E3+E4+E5+E6 | F7: =F3+F4+F5+F6
A8: 应付 AP | B8: 1037.06 | C8: =WorkingCapital!C5 | D8: =WorkingCapital!D5 | E8: =WorkingCapital!E5 | F8: =WorkingCapital!F5
A9: 有息负债 Debt | B9: 10711.44 | C9: =DebtSchedule!C5 | D9: =DebtSchedule!D5 | E9: =DebtSchedule!E5 | F9: =DebtSchedule!F5
A10: 负债合计 Total liab | B10: =B8+B9 | C10: =C8+C9 | D10: =D8+D9 | E10: =E8+E9 | F10: =F8+F9
A11: 所有者权益 Equity | B11: 5958.56 | C11: =B11+IncomeStatement!C12 | D11: =C11+IncomeStatement!D12 | E11: =D11+IncomeStatement!E12 | F11: =E11+IncomeStatement!F12
A12: 负债+权益 Total L&E | B12: =B10+B11 | C12: =C10+C11 | D12: =D10+D11 | E12: =E10+E11 | F12: =F10+F11
A13: 平衡校验 Check(=0) | B13: =B7-B12 | C13: =C7-C12 | D13: =D7-D12 | E13: =E7-E12 | F13: =F7-F12

Sheet DCF
A1: 现金流折现估值 DCF Valuation
A2: 项目 \ 年度 | B2: 期初 t0 | C2: 2025 | D2: 2026 | E2: 2027 | F2: 2028
A3: EBIT | C3: =IncomeStatement!C8 | D3: =IncomeStatement!D8 | E3: =IncomeStatement!E8 | F3: =IncomeStatement!F8
A4: NOPAT=EBIT×(1-tax) | C4: =C3*(1-Assumptions!B6) | D4: =D3*(1-Assumptions!B6) | E4: =E3*(1-Assumptions!B6) | F4: =F3*(1-Assumptions!B6)
A5: 加:D&A | C5: =PPE!C6 | D5: =PPE!D6 | E5: =PPE!E6 | F5: =PPE!F6
A6: 减:Capex | C6: =-PPE!C4 | D6: =-PPE!D4 | E6: =-PPE!E4 | F6: =-PPE!F4
A7: 减:ΔNWC | C7: =-WorkingCapital!C7 | D7: =-WorkingCapital!D7 | E7: =-WorkingCapital!E7 | F7: =-WorkingCapital!F7
A8: 无杠杆自由现金流 FCFF | C8: =C4+C5+C6+C7 | D8: =D4+D5+D6+D7 | E8: =E4+E5+E6+E7 | F8: =F4+F5+F6+F7
A9: 折现因子 DF | C9: =1/(1+Assumptions!B13)^(1-0.5) | D9: =1/(1+Assumptions!B13)^(2-0.5) | E9: =1/(1+Assumptions!B13)^(3-0.5) | F9: =1/(1+Assumptions!B13)^(4-0.5)
A10: FCF现值 PV | C10: =C8*C9 | D10: =D8*D9 | E10: =E8*E9 | F10: =F8*F9
A12: 预测期PV合计 Σ PV(FCF) | B12: =SUM(C10:F10)
A13: 终值 Terminal value | B13: =F3*Assumptions!B23
A14: 终值现值 PV(TV) | B14: =B13*F9
A15: 企业价值 Enterprise value | B15: =B12+B14
A16: 净负债 Net debt | B16: =Assumptions!B19-Assumptions!B16
A17: 股权价值 Equity value | B17: =B15-B16
A18: 每股价值 Value per share | B18: =B17/Assumptions!B15

Sheet 旧版测算_废弃
A1: ⚠ DEPRECATED — 请勿引用此表 / do not reference
A2: 项目 Item | B2: 金额 Amount | C2: 备注 Note | D2: 日期
A3: 预留 | B3: 10125.96 | C3: old
A4: TBD | B4: 60778.16 | C4: check later
A5: Misc | B5: 32955.67 | C5: 废弃
A6: 杂项 | B6: 72787.32
A7: 调整 | B7: 87690.09 | C7: check later
A8: 杂项 | B8: 20827.27 | C8: check later
A9: TBD | B9: 52874.05 | C9: 废弃
A10: Misc | B10: 85742.88 | C10: 废弃
A11: 杂项 | B11: 23768.26 | C11: check later

Sheet Scratch
A1: ⚠ DEPRECATED — 请勿引用此表 / do not reference
A2: 项目 Item | B2: 金额 Amount | C2: 备注 Note | D2: 日期
A3: Misc | B3: 65949.58 | C3: check later
A4: Misc | B4: 27523.04 | C4: old
A5: 预留 | B5: 29946.5
A6: 预留 | B6: 56142.8
A7: 预留 | B7: 1160.62 | C7: check later
A8: TBD | B8: 18625.24 | C8: check later
A9: 调整 | B9: 46449.97 | C9: 废弃
A10: 杂项 | B10: 37093.76
A11: 杂项 | B11: 69470.45 | C11: old
A12: 预留 | B12: 6822.65 | C12: 废弃
A13: 预留 | B13: 59836.45 | C13: check later
A14: 调整 | B14: 82969.49 | C14: 废弃
A15: Misc | B15: 89452.13 | C15: old
